{
	"name": "TrainPlaceholder2",
	"plugin-id": "Sprite",
	"sid": 889620781761143,
	"isGlobal": false,
	"instanceVariables": [],
	"behaviorTypes": [
		{
			"behaviorId": "solid",
			"name": "Solid",
			"sid": 721534700366878
		},
		{
			"behaviorId": "Sin",
			"name": "Sine",
			"sid": 637704800363648
		}
	],
	"effectTypes": [],
	"animations": {
		"items": [
			{
				"frames": [
					{
						"width": 798,
						"height": 568,
						"originX": 0.5037593984962406,
						"originY": 0.29401408450704225,
						"originalSource": "",
						"exportFormat": "png",
						"exportQuality": 0.8,
						"imageSpriteId": 832741,
						"collisionPoly": {
							"points": [
								0.16290707695753054,
								0.19718311202358185,
								0.9598997876160127,
								0.19014083163838982,
								1,
								0.8538732931647496,
								0.17042614164806547,
								0.882042280385191,
								0,
								0.5941902012892171
							]
						},
						"useCollisionPoly": true,
						"duration": 1
					}
				],
				"sid": 154521631417396,
				"name": "Animation 1",
				"isLooping": false,
				"isPingPong": false,
				"repeatCount": 1,
				"repeatTo": 0,
				"speed": 5
			}
		],
		"subfolders": []
	}
}